{
   "runs" : [
      {
         "OS" : "linux",
         "abstract" : "Runtime Configuration for an Object",
         "dir" : "/home/runner/work/Object-Configure/Object-Configure",
         "finish" : 1757007314.06872,
         "name" : "Object-Configure",
         "perl" : "5.40.3",
         "run" : "-e",
         "start" : 1757007314.06843,
         "version" : 0.14
      },
      {
         "OS" : "linux",
         "abstract" : "Runtime Configuration for an Object",
         "dir" : "/home/runner/work/Object-Configure/Object-Configure",
         "finish" : 1757007314.22986,
         "name" : "Object-Configure",
         "perl" : "5.40.3",
         "run" : "-e",
         "start" : 1757007314.22963,
         "version" : 0.14
      },
      {
         "OS" : "linux",
         "abstract" : "Runtime Configuration for an Object",
         "dir" : "/home/runner/work/Object-Configure/Object-Configure",
         "finish" : 1757007314.39405,
         "name" : "Object-Configure",
         "perl" : "5.40.3",
         "run" : "-e",
         "start" : 1757007314.39374,
         "version" : 0.14
      },
      {
         "OS" : "linux",
         "abstract" : "Runtime Configuration for an Object",
         "dir" : "/home/runner/work/Object-Configure/Object-Configure",
         "finish" : 1757007314.55708,
         "name" : "Object-Configure",
         "perl" : "5.40.3",
         "run" : "-e",
         "start" : 1757007314.5568,
         "version" : 0.14
      },
      {
         "OS" : "linux",
         "abstract" : "Runtime Configuration for an Object",
         "dir" : "/home/runner/work/Object-Configure/Object-Configure",
         "finish" : 1757007314.71995,
         "name" : "Object-Configure",
         "perl" : "5.40.3",
         "run" : "-e",
         "start" : 1757007314.71967,
         "version" : 0.14
      },
      {
         "OS" : "linux",
         "abstract" : "Runtime Configuration for an Object",
         "dir" : "/home/runner/work/Object-Configure/Object-Configure",
         "finish" : 1757007314.88908,
         "name" : "Object-Configure",
         "perl" : "5.40.3",
         "run" : "-e",
         "start" : 1757007314.88884,
         "version" : 0.14
      },
      {
         "OS" : "linux",
         "abstract" : "Runtime Configuration for an Object",
         "dir" : "/home/runner/work/Object-Configure/Object-Configure",
         "finish" : 1757007315.06069,
         "name" : "Object-Configure",
         "perl" : "5.40.3",
         "run" : "-e",
         "start" : 1757007315.06038,
         "version" : 0.14
      },
      {
         "OS" : "linux",
         "abstract" : "Runtime Configuration for an Object",
         "dir" : "/home/runner/work/Object-Configure/Object-Configure",
         "finish" : 1757007315.22819,
         "name" : "Object-Configure",
         "perl" : "5.40.3",
         "run" : "-e",
         "start" : 1757007315.22787,
         "version" : 0.14
      },
      {
         "OS" : "linux",
         "abstract" : "Runtime Configuration for an Object",
         "dir" : "/home/runner/work/Object-Configure/Object-Configure",
         "finish" : 1757007315.41297,
         "name" : "Object-Configure",
         "perl" : "5.40.3",
         "run" : "-e",
         "start" : 1757007315.40455,
         "version" : 0.14
      },
      {
         "OS" : "linux",
         "abstract" : "Runtime Configuration for an Object",
         "dir" : "/home/runner/work/Object-Configure/Object-Configure",
         "finish" : 1757007318.7894,
         "name" : "Object-Configure",
         "perl" : "5.40.3",
         "run" : "-e",
         "start" : 1757007315.61402,
         "version" : 0.14
      },
      {
         "OS" : "linux",
         "abstract" : "Runtime Configuration for an Object",
         "dir" : "/home/runner/work/Object-Configure/Object-Configure",
         "finish" : 1757007315.75963,
         "name" : "Object-Configure",
         "perl" : "5.40.3",
         "run" : "-e",
         "start" : 1757007315.75954,
         "version" : 0.14
      },
      {
         "OS" : "linux",
         "abstract" : "Runtime Configuration for an Object",
         "dir" : "/home/runner/work/Object-Configure/Object-Configure",
         "finish" : 1757007316.06774,
         "name" : "Object-Configure",
         "perl" : "5.40.3",
         "run" : "t/30-basics.t",
         "start" : 1757007316.05938,
         "version" : 0.14
      },
      {
         "OS" : "linux",
         "abstract" : "Runtime Configuration for an Object",
         "dir" : "/home/runner/work/Object-Configure/Object-Configure",
         "finish" : 1757007316.44184,
         "name" : "Object-Configure",
         "perl" : "5.40.3",
         "run" : "t/complex.t",
         "start" : 1757007316.41616,
         "version" : 0.14
      },
      {
         "OS" : "linux",
         "abstract" : "Runtime Configuration for an Object",
         "dir" : "/home/runner/work/Object-Configure/Object-Configure",
         "finish" : 1757007316.81025,
         "name" : "Object-Configure",
         "perl" : "5.40.3",
         "run" : "t/env.t",
         "start" : 1757007316.78597,
         "version" : 0.14
      },
      {
         "OS" : "linux",
         "abstract" : "Runtime Configuration for an Object",
         "dir" : "/home/runner/work/Object-Configure/Object-Configure",
         "finish" : 1757007317.08385,
         "name" : "Object-Configure",
         "perl" : "5.40.3",
         "run" : "t/eof.t",
         "start" : 1757007317.0836,
         "version" : 0.14
      },
      {
         "OS" : "linux",
         "abstract" : "Runtime Configuration for an Object",
         "dir" : "/home/runner/work/Object-Configure/Object-Configure",
         "finish" : 1757007317.31677,
         "name" : "Object-Configure",
         "perl" : "5.40.3",
         "run" : "t/eol.t",
         "start" : 1757007317.31653,
         "version" : 0.14
      },
      {
         "OS" : "linux",
         "abstract" : "Runtime Configuration for an Object",
         "dir" : "/home/runner/work/Object-Configure/Object-Configure",
         "finish" : 1757007317.63819,
         "name" : "Object-Configure",
         "perl" : "5.40.3",
         "run" : "t/instantiate.t",
         "start" : 1757007317.59866,
         "version" : 0.14
      },
      {
         "OS" : "linux",
         "abstract" : "Runtime Configuration for an Object",
         "dir" : "/home/runner/work/Object-Configure/Object-Configure",
         "finish" : 1757007317.9107,
         "name" : "Object-Configure",
         "perl" : "5.40.3",
         "run" : "t/pod-cm.t",
         "start" : 1757007317.91044,
         "version" : 0.14
      },
      {
         "OS" : "linux",
         "abstract" : "Runtime Configuration for an Object",
         "dir" : "/home/runner/work/Object-Configure/Object-Configure",
         "finish" : 1757007318.14575,
         "name" : "Object-Configure",
         "perl" : "5.40.3",
         "run" : "t/pod-synopsis.t",
         "start" : 1757007318.14551,
         "version" : 0.14
      },
      {
         "OS" : "linux",
         "abstract" : "Runtime Configuration for an Object",
         "dir" : "/home/runner/work/Object-Configure/Object-Configure",
         "finish" : 1757007318.37813,
         "name" : "Object-Configure",
         "perl" : "5.40.3",
         "run" : "t/pod.t",
         "start" : 1757007318.37787,
         "version" : 0.14
      },
      {
         "OS" : "linux",
         "abstract" : "Runtime Configuration for an Object",
         "dir" : "/home/runner/work/Object-Configure/Object-Configure",
         "finish" : 1757007318.70669,
         "name" : "Object-Configure",
         "perl" : "5.40.3",
         "run" : "t/simple.t",
         "start" : 1757007318.67857,
         "version" : 0.14
      }
   ],
   "summary" : {
      "Total" : {
         "branch" : {
            "covered" : 18,
            "error" : 8,
            "percentage" : 69.2307692307692,
            "total" : 26,
            "uncoverable" : 0
         },
         "condition" : {
            "covered" : 8,
            "error" : 8,
            "percentage" : 50,
            "total" : 16,
            "uncoverable" : 0
         },
         "statement" : {
            "covered" : 53,
            "error" : 6,
            "percentage" : 89.8305084745763,
            "total" : 59
         },
         "subroutine" : {
            "covered" : 10,
            "percentage" : 100,
            "total" : 10
         },
         "total" : {
            "covered" : 89,
            "error" : 22,
            "percentage" : 80.1801801801802,
            "total" : 111,
            "uncoverable" : 0
         }
      },
      "blib/lib/Object/Configure.pm" : {
         "branch" : {
            "covered" : 18,
            "error" : 8,
            "percentage" : 69.2307692307692,
            "total" : 26,
            "uncoverable" : 0
         },
         "condition" : {
            "covered" : 8,
            "error" : 8,
            "percentage" : 50,
            "total" : 16,
            "uncoverable" : 0
         },
         "statement" : {
            "covered" : 53,
            "error" : 6,
            "percentage" : 89.8305084745763,
            "total" : 59
         },
         "subroutine" : {
            "covered" : 10,
            "percentage" : 100,
            "total" : 10
         },
         "total" : {
            "covered" : 89,
            "error" : 22,
            "percentage" : 80.1801801801802,
            "total" : 111,
            "uncoverable" : 0
         }
      }
   }
}
